{
	"-log10(ε)": 3,
	"1/α (x)": 0.5,
	"1/β (x)": 2.5,
	"Adiabatic Index": 1.4,
	"Aerodynamic Drag": true,
	"Ambient Density (kg/m³)": 1.204,
	"Ambient Pressure (kPa)": 101.325,
	"Autofrettage": true,
	"Auxiliary 1/α (x)": 1.0,
	"Auxiliary 1/β (x)": 250.0,
	"Auxiliary Grain Geometry": "TUBE",
	"Calculate Structure": false,
	"Caliber (mm)": 85.0,
	"Chamber Volume (L)": 5.441,
	"Chambrage Ratio (x)": 1.725,
	"Charge / Shot Mass Step": 0.05,
	"Charge Mass (kg)": 4.15,
	"Constrain Design": true,
	"Constrain Travel": true,
	"Description": "Ballistics of the Type 1972 Anti-Aircraft Gun firing Airburst Fragmentation (Time Fuzed) shell, industrial designation WB030AP.\n\nCaliber:                85 mm\nProjectile Weight:     9.3 kg\nGun Length:           6022 mm\nBarrel Length:        5500 mm\nProjectile Travel:    4965 mm\nPropellant:           4.15 kg Pyroxylin (16/7 Rosette + 18/1-42), assumed 4:1.\nMuzzle Velocity:      1000 m/s\nPeak Pressure:  3100(3150) kgf/cm^2 (space mean), \nChamber Volume:      5.441 L\nChamber Length:       5.35 dm (interior)\nChambrage:           1.725 (estimated) ",
	"Expansion Ratio (x)": 4.0,
	"Gas Gradient": "SOL_LAGRANGE",
	"Grain Geometry": "SEVEN_PERF_ROSETTE",
	"Gun Type": "CONVENTIONAL",
	"Load Condition": "USE_CV",
	"Load Density (kg/m³)": 762.7,
	"Load Factor (%)": 47.67,
	"Load Fraction Step (%)": 5.0,
	"Mass Aux / Main (x)": 0.25,
	"Material Density (kg/m³)": 7850.0,
	"Max Charge / Shot Mass": 1.75,
	"Max Guess": 25,
	"Max Iteration": 10,
	"Max Length (m)": 100.0,
	"Max Load Fraction (%)": 90.0,
	"Min Charge / Shot Mass": 0.25,
	"Min Load Fraction (%)": 10.0,
	"Minimize Total Volume": false,
	"Minimum Web (μm)": 1.0,
	"Mixed Charge": true,
	"Nozzle Efficiency (%)": 92.0,
	"Pressure Constraint": "PEAK_AVG_P",
	"Pressure Target (MPa)": 314.0,
	"Propellant": "Pyroxylin",
	"Resistance Factor (%)": 3.0,
	"Safety Factor": 1.35,
	"Sampling Points": "DOMAIN_TIME",
	"Shot Mass (kg)": 9.3,
	"Start Pressure (MPa)": 30.0,
	"Steps": 33,
	"Travel (mm)": 4965.0,
	"Velocity Target (m/s)": 1000.0,
	"Web (mm)": 2.025,
	"Web Aux / Main (x)": 1.136,
	"Yield Strength (MPa)": 1000.0
}